CHANGES.txt
CONTRIBUTORS.txt
KNOWN_ISSUES.txt
README.txt
setup.py
collective/__init__.py
collective.facetsupport.egg-info/PKG-INFO
collective.facetsupport.egg-info/SOURCES.txt
collective.facetsupport.egg-info/dependency_links.txt
collective.facetsupport.egg-info/entry_points.txt
collective.facetsupport.egg-info/namespace_packages.txt
collective.facetsupport.egg-info/not-zip-safe
collective.facetsupport.egg-info/requires.txt
collective.facetsupport.egg-info/top_level.txt
collective/facetsupport/TODO.txt
collective/facetsupport/__init__.py
collective/facetsupport/adapters.py
collective/facetsupport/config.py
collective/facetsupport/configure.zcml
collective/facetsupport/interfaces.py
collective/facetsupport/browser/__init__.py
collective/facetsupport/browser/configure.zcml
collective/facetsupport/browser/inline_facet_menu.pt
collective/facetsupport/browser/inline_facet_result.pt
collective/facetsupport/browser/views.py
collective/facetsupport/tests/__init__.py
collective/facetsupport/tests/base.py
collective/facetsupport/tests/browser.txt
collective/facetsupport/tests/dummy_content.py
collective/facetsupport/tests/facet_builder.txt
collective/facetsupport/tests/test_doc.py
collective/facetsupport/tests/test_integration.py
docs/INSTALL.txt
docs/LICENSE.GPL
docs/LICENSE.txt