Metadata-Version: 1.0
Name: collective.facetsupport
Version: 0.1a
Summary: Tools for generating facets for content in Plone
Home-page: https://svn.plone.org/svn/collective/collective.facetsupport
Author: Robin Harms Oredsson
Author-email: robin@betahaus.net
License: GPL
Keywords: plone
Platform: UNKNOWN
Classifier: Framework :: Plone
Classifier: Programming Language :: Python
Classifier: Development Status :: 3 - Alpha
Classifier: Intended Audience :: Developers
Classifier: License :: OSI Approved :: GNU General Public License (GPL)
